cougar_log/__init__.py
cougar_log/data_log_reader.py
cougar_log/log_helpers.py
cougar_log/main.py
cougar_log/ssh_download.py
cougar_log-0.1.3.dist-info/entry_points.txt
cougar_log-0.1.3.dist-info/WHEEL
cougar_log-0.1.3.dist-info/METADATA
cougar_log-0.1.3.dist-info/RECORD
